[
  {
    "text": "Giving yourself permission to prioritize your goals over social events is key to consistency. I'm still figuring out my routine, but it's worth the sacrifice for my dreams",
    "tone": "motivational",
    "format": "micro-lesson",
    "pillar": [
      "motivation",
      "consistency"
    ],
    "psychological_trigger": "permission_slip",
    "hook_template_id": null,
    "audience_fit": {
      "pain_point": "feeling stuck",
      "desire": "visible physical progress"
    },
    "goal_alignment": {
      "stage": "cold",
      "objective": "follower_growth"
    },
    "arc_phase": "beginning",
    "hashtags": [],
    "quality_score": 8.2,
    "quality_breakdown": {
      "clarity": 8.5,
      "originality": 7.8,
      "emotional_impact": 8,
      "virality_potential": 8.5,
      "audience_fit": 8
    },
    "decision_reason": "Aligns with the audience's desire for visible physical progress and feeling stuck"
  },
  {
    "text": "What's the smallest habit you can commit to daily? For me, it's 10 minutes of exercise. 10 minutes a day can be the start of a consistent routine",
    "tone": "casual",
    "format": "question",
    "pillar": [
      "consistency",
      "motivation"
    ],
    "psychological_trigger": "specificity_shock",
    "hook_template_id": null,
    "audience_fit": {
      "pain_point": "losing consistency after 2-3 weeks",
      "desire": "purposeful daily routine"
    },
    "goal_alignment": {
      "stage": "cold",
      "objective": "follower_growth"
    },
    "arc_phase": "beginning",
    "hashtags": [],
    "quality_score": 7.9,
    "quality_breakdown": {
      "clarity": 8,
      "originality": 7.5,
      "emotional_impact": 7.8,
      "virality_potential": 8,
      "audience_fit": 8
    },
    "decision_reason": "Encourages the audience to think about their daily habits and routines"
  },
  {
    "text": "3 things that happen when you give up on consistency: you lose momentum, you feel guilty, and you drift away from your goals. Don't let that be you",
    "tone": "reflective",
    "format": "list",
    "pillar": [
      "life",
      "consistency"
    ],
    "psychological_trigger": "stakes_escalation",
    "hook_template_id": null,
    "audience_fit": {
      "pain_point": "feeling stuck",
      "desire": "being someone people notice changed"
    },
    "goal_alignment": {
      "stage": "cold",
      "objective": "follower_growth"
    },
    "arc_phase": "beginning",
    "hashtags": [],
    "quality_score": 8.5,
    "quality_breakdown": {
      "clarity": 8.8,
      "originality": 8,
      "emotional_impact": 8.5,
      "virality_potential": 8.8,
      "audience_fit": 8.5
    },
    "decision_reason": "Highlights the consequences of giving up on consistency and encourages the audience to take action"
  }
]